examples/__init__.py
examples/get_token.py
examples/info.py
examples/link.py
examples/me.py
examples/profiles.py
examples/update.py
examples/updates_and_profiles.py
puffer/__init__.py
puffer/api.py
puffer/response.py
puffer/test.py
puffer/managers/__init__.py
puffer/managers/profiles.py
puffer/managers/updates.py
puffer/models/__init__.py
puffer/models/link.py
puffer/models/profile.py
puffer/models/update.py
puffer/models/user.py
puffer/tests/__init__.py
puffer/tests/test_api.py
puffer/tests/test_link.py
puffer/tests/test_profile.py
puffer/tests/test_profiles_manager.py
puffer/tests/test_response.py
puffer/tests/test_update.py
puffer/tests/test_updates_manager.py
puffer/tests/test_user.py
puffer-1.8.2.dist-info/DESCRIPTION.rst
puffer-1.8.2.dist-info/METADATA
puffer-1.8.2.dist-info/RECORD
puffer-1.8.2.dist-info/WHEEL
puffer-1.8.2.dist-info/metadata.json
puffer-1.8.2.dist-info/top_level.txt
