Metadata-Version: 2.0
Name: puffer
Version: 1.8.2
Summary: Python wrapper for the Buffer API
Home-page: https://github.com/villasv/puffer
Author: Vlad Temian, Victor Villas
Author-email: villasv@outlook.com
License: UNKNOWN
Platform: any
Classifier: Programming Language :: Python :: 3.5
Requires-Dist: colorama (==0.2.7)
Requires-Dist: coverage (==3.7.1)
Requires-Dist: mock (==1.0.1)
Requires-Dist: nose (==1.3.0)
Requires-Dist: rauth (==0.7.2)
Requires-Dist: requests (==2.10.0)
